fast_IO/__init__.py
fast_IO-0.0.1.dist-info/METADATA
fast_IO-0.0.1.dist-info/WHEEL
fast_IO-0.0.1.dist-info/top_level.txt
fast_IO-0.0.1.dist-info/RECORD
