Metadata-Version: 2.1
Name: fast_IO
Version: 0.0.1
Summary: fast IO for pypy3 and python3
Home-page: UNKNOWN
License: UNKNOWN
Platform: UNKNOWN
